<?xml version="1.0" encoding="utf-8"?>
<publishData>
  <publishProfile publishUrl="E:\Rajib's Folder\SKFJISuvojitNew[15.05.2017]\SKFGI\BUILD_23_05_2017" deleteExistingFiles="True" ftpAnonymousLogin="False" ftpPassiveMode="True" msdeploySite="" msdeploySiteID="" msdeployRemoteSitePhysicalPath="" msdeployAllowUntrustedCertificate="False" msdeploySkipExtraFilesOnServer="True" msdeployMarkAsApp="False" profileName="Profile1" publishMethod="FileSystem" replaceMatchingFiles="False" userName="" savePWD="False" userPWD="" SelectedForPublish="True">
    <file relUrl="Student/PopUpStudentSubjectMappingUpdate.aspx" publishTime="08/26/2015 11:28:45" />
    <file relUrl="Images/Management.png" publishTime="08/26/2015 11:28:36" />
    <file relUrl="Images/logo.png" publishTime="08/26/2015 11:28:36" />
    <file relUrl="Student/printFeesVoucher.aspx" publishTime="08/26/2015 11:28:45" />
    <file relUrl="Accounts/RPTBrs.aspx" publishTime="08/26/2015 11:28:30" />
    <file relUrl="Common/AddEditEmployee.aspx" publishTime="11/12/2015 15:20:56" />
    <file relUrl="Accounts/ChangeCompany.aspx" publishTime="08/26/2015 11:28:29" />
    <file relUrl="Images/quick_l_selected.png" publishTime="08/26/2015 11:28:36" />
    <file relUrl="Student/StudentPromotion.aspx" publishTime="08/26/2015 11:28:46" />
    <file relUrl="HR/ApplyClaim.aspx" publishTime="08/26/2015 11:28:33" />
    <file relUrl="Common/CategoryMaster.aspx" publishTime="08/26/2015 11:28:31" />
    <file relUrl="Images/IDCardHeader.JPG" publishTime="08/26/2015 11:28:35" />
    <file relUrl="Images/menu_border.png" publishTime="08/26/2015 11:28:36" />
    <file relUrl="Login.aspx" publishTime="08/26/2015 11:31:20" />
    <file relUrl="Images/Google.jpg" publishTime="08/26/2015 11:28:35" />
    <file relUrl="Images/YES.JPG" publishTime="08/26/2015 11:28:37" />
    <file relUrl="HR/LeaveDeleteList.aspx" publishTime="08/26/2015 11:28:34" />
    <file relUrl="Scripts/tiny_mce.js" publishTime="08/26/2015 11:28:44" />
    <file relUrl="Payroll/PopupSalaryHeadDetails.aspx" publishTime="08/26/2015 11:28:38" />
    <file relUrl="Accounts/StudentCautionMoneyRefund.aspx" publishTime="08/26/2015 11:28:31" />
    <file relUrl="Scripts/smooth.table.js" publishTime="08/26/2015 11:28:44" />
    <file relUrl="Student/ApproveHostelList.aspx" publishTime="08/26/2015 11:28:44" />
    <file relUrl="Images/AboutUs.JPG" publishTime="08/26/2015 11:28:35" />
    <file relUrl="Images/bg.JPG" publishTime="08/26/2015 11:28:35" />
    <file relUrl="Common/EmployeeAttendance.aspx" publishTime="08/26/2015 11:28:31" />
    <file relUrl="Images/DiplomaHeader.JPG" publishTime="08/26/2015 11:28:35" />
    <file relUrl="bin/office.xml" publishTime="01/18/2011 21:08:54" />
    <file relUrl="Images/Headerbg.JPG" publishTime="08/26/2015 11:28:35" />
    <file relUrl="Student/MBARegistrationPrint.aspx" publishTime="07/18/2016 16:28:40" />
    <file relUrl="Common/PopUpRole.aspx" publishTime="08/26/2015 11:28:32" />
    <file relUrl="bin/Entity.dll" publishTime="05/22/2017 17:24:20" />
    <file relUrl="Images/newLeft.gif" publishTime="08/26/2015 11:28:36" />
    <file relUrl="Images/menu_selected.png" publishTime="08/26/2015 11:28:36" />
    <file relUrl="bin/AjaxControlToolkit.dll" publishTime="08/13/2012 00:56:30" />
    <file relUrl="Accounts/BankAccount.aspx" publishTime="08/26/2015 11:28:29" />
    <file relUrl="Unauthorized.aspx" publishTime="08/26/2015 11:31:20" />
    <file relUrl="Common/StreamMaster.aspx" publishTime="08/26/2015 11:28:32" />
    <file relUrl="Student/StudentPhoto/6490.jpg" publishTime="08/26/2015 11:28:46" />
    <file relUrl="Student/DiplomaRegistration.aspx" publishTime="08/02/2016 15:38:33" />
    <file relUrl="Student/NewAdmissionReport.aspx" publishTime="08/26/2015 11:28:45" />
    <file relUrl="Accounts/TrialBalance.aspx" publishTime="08/26/2015 11:28:31" />
    <file relUrl="Accounts/RTPReceiptPaymentAccount.aspx" publishTime="11/17/2015 11:52:07" />
    <file relUrl="bin/itextsharp.dll" publishTime="02/05/2013 13:41:20" />
    <file relUrl="Common/PopUpTermsAndCondition.aspx" publishTime="08/26/2015 11:28:32" />
    <file relUrl="HR/ApplyLeaves.aspx" publishTime="08/26/2015 11:28:33" />
    <file relUrl="Images/plus.JPG" publishTime="08/26/2015 11:28:36" />
    <file relUrl="HR/ClaimList.aspx" publishTime="08/26/2015 11:28:33" />
    <file relUrl="Payroll/EmployeeIncrementList.aspx" publishTime="08/26/2015 11:28:37" />
    <file relUrl="HR/LeaveReport.aspx" publishTime="08/26/2015 11:28:34" />
    <file relUrl="Accounts/PLTransfer.aspx" publishTime="03/05/2016 13:46:38" />
    <file relUrl="Student/MTechRegistrationPrint.aspx" publishTime="07/18/2016 16:09:18" />
    <file relUrl="Accounts/MoneyReceiptDiploma.aspx" publishTime="08/26/2015 11:28:30" />
    <file relUrl="Student/LibraryFine.aspx" publishTime="08/26/2015 11:28:45" />
    <file relUrl="Accounts/StudentCautionMoneyIndividualReport.aspx" publishTime="08/26/2015 11:28:31" />
    <file relUrl="Common/PopUpLeaveDetail.aspx" publishTime="08/26/2015 11:28:32" />
    <file relUrl="Styles/blue.css" publishTime="08/26/2015 11:28:46" />
    <file relUrl="Images/plus.gif" publishTime="08/26/2015 11:28:36" />
    <file relUrl="Payroll/IndividualSalaryDeatails.aspx" publishTime="08/26/2015 11:28:37" />
    <file relUrl="Accounts/ExpenseReimbursement.aspx" publishTime="08/26/2015 11:28:30" />
    <file relUrl="Images/Home.JPG" publishTime="08/26/2015 11:28:35" />
    <file relUrl="Images/ReportHeader.png" publishTime="08/26/2015 11:28:36" />
    <file relUrl="Images/quick_l.png" publishTime="08/26/2015 11:28:36" />
    <file relUrl="UserControl/menu.ascx" publishTime="05/22/2017 17:23:45" />
    <file relUrl="Payroll/MonthlyESIRegister.aspx" publishTime="08/26/2015 11:28:38" />
    <file relUrl="Accounts/CashBankVoucher.aspx" publishTime="08/26/2015 11:28:29" />
    <file relUrl="Common/CityMaster.aspx" publishTime="08/26/2015 11:28:31" />
    <file relUrl="Common/PopupFamilyDetails.aspx" publishTime="08/26/2015 11:28:32" />
    <file relUrl="Accounts/RPTGridView.aspx" publishTime="08/26/2015 11:28:30" />
    <file relUrl="Accounts/App_LocalResources/MoneyReceipt.aspx.resx" publishTime="08/26/2015 11:28:29" />
    <file relUrl="ChangePassword.aspx" publishTime="08/26/2015 11:31:22" />
    <file relUrl="bin/Entity.pdb" publishTime="05/22/2017 17:24:20" />
    <file relUrl="Scripts/ssjscript.js" publishTime="08/26/2015 11:28:44" />
    <file relUrl="Accounts/RptStudentFeesCollection.aspx" publishTime="08/26/2015 11:28:30" />
    <file relUrl="Accounts/DebitNote.aspx" publishTime="08/26/2015 11:28:30" />
    <file relUrl="bin/SKFGI.dll" publishTime="05/23/2017 16:37:37" />
    <file relUrl="Student/SemFeesGeneration.aspx" publishTime="08/26/2015 11:28:45" />
    <file relUrl="Images/menu_plus.png" publishTime="08/26/2015 11:28:36" />
    <file relUrl="Home.Master" publishTime="01/13/2017 12:36:02" />
    <file relUrl="Payroll/ITaxPrevEmplHeads.aspx" publishTime="08/26/2015 11:28:38" />
    <file relUrl="Images/world_link.png" publishTime="08/26/2015 11:28:37" />
    <file relUrl="Common/HolidayList.aspx" publishTime="08/26/2015 11:28:32" />
    <file relUrl="UserControl/LeftNav.ascx" publishTime="05/22/2017 17:22:56" />
    <file relUrl="Student/AttendanceReport.aspx" publishTime="08/26/2015 16:44:11" />
    <file relUrl="Scripts/webtrends.min.js" publishTime="08/26/2015 11:28:44" />
    <file relUrl="Accounts/RPTUserBaseCashBankVoucher.aspx" publishTime="08/26/2015 11:28:30" />
    <file relUrl="Accounts/RPTJournalRegister.aspx" publishTime="08/26/2015 11:28:30" />
    <file relUrl="Images/menu_minus.PNG" publishTime="08/26/2015 11:28:36" />
    <file relUrl="Images/install_button.jpg" publishTime="08/26/2015 11:28:35" />
    <file relUrl="Images/warning.gif" publishTime="08/26/2015 11:28:37" />
    <file relUrl="Accounts/JournalVoucher.aspx" publishTime="08/26/2015 11:28:30" />
    <file relUrl="Accounts/StudentJournal.aspx" publishTime="08/26/2015 11:28:31" />
    <file relUrl="Accounts/RPTCostCenterWiseReport.aspx" publishTime="08/26/2015 11:28:30" />
    <file relUrl="Scripts/scw.js" publishTime="08/26/2015 11:28:44" />
    <file relUrl="Student/ApproveHostel.aspx" publishTime="08/26/2015 11:28:44" />
    <file relUrl="Images/quick_r_selected.png" publishTime="08/26/2015 11:28:36" />
    <file relUrl="Accounts/RPTGeneralLedgerBalance.aspx" publishTime="08/26/2015 11:28:30" />
    <file relUrl="Images/success.png" publishTime="08/26/2015 11:28:36" />
    <file relUrl="Accounts/RPTCashBankVoucher.aspx" publishTime="08/26/2015 11:28:30" />
    <file relUrl="Images/quick_r.png" publishTime="08/26/2015 11:28:36" />
    <file relUrl="bin/office.dll" publishTime="01/18/2011 18:27:04" />
    <file relUrl="Student/PopUpLibraryFineVoucher.aspx" publishTime="08/26/2015 11:28:45" />
    <file relUrl="Student/StudentPhoto/8.jpg" publishTime="08/26/2015 11:28:46" />
    <file relUrl="Scripts/jquery-1.7.1.min.js" publishTime="08/26/2015 11:28:44" />
    <file relUrl="Images/New_Icon.jpg" publishTime="08/26/2015 11:28:36" />
    <file relUrl="Student/StudentPhoto/29.jpg" publishTime="08/26/2015 11:28:46" />
    <file relUrl="Payroll/PTaxSummeryReport.aspx" publishTime="04/13/2017 16:18:12" />
    <file relUrl="Styles/Print.css" publishTime="08/26/2015 11:28:46" />
    <file relUrl="Payroll/MonthlyPTaxRegister.aspx" publishTime="08/26/2015 11:28:38" />
    <file relUrl="Student/StudentIDCard.aspx" publishTime="08/26/2015 11:28:46" />
    <file relUrl="HR/EmployeeDetail.aspx" publishTime="01/16/2017 13:17:35" />
    <file relUrl="Common/BranchMaster.aspx" publishTime="08/26/2015 11:28:31" />
    <file relUrl="Accounts/StudentPaymentDetails.aspx" publishTime="08/26/2015 11:28:31" />
    <file relUrl="Common/AppointmentLetter.aspx" publishTime="08/26/2015 11:28:31" />
    <file relUrl="Payroll/ITaxInvestmentHeads.aspx" publishTime="08/26/2015 11:28:37" />
    <file relUrl="Accounts/PrintDebitNote.aspx" publishTime="08/26/2015 11:28:30" />
    <file relUrl="Scripts/jquery.tinymce.js" publishTime="08/26/2015 11:28:44" />
    <file relUrl="Accounts/GeneralLedger.aspx" publishTime="02/25/2016 12:16:33" />
    <file relUrl="Student/HostelFeesGeneration.aspx" publishTime="08/26/2015 11:28:45" />
    <file relUrl="Accounts/RPTPurchaseBillPayment.aspx" publishTime="08/26/2015 11:28:30" />
    <file relUrl="Student/StudentSectionMapping.aspx" publishTime="08/26/2015 11:28:46" />
    <file relUrl="Payroll/Form16Generate.aspx" publishTime="08/26/2015 11:28:37" />
    <file relUrl="Global.asax" publishTime="08/26/2015 11:31:19" />
    <file relUrl="Common/PopupWorkDetails.aspx" publishTime="08/26/2015 11:28:32" />
    <file relUrl="Images/menu_arrow.png" publishTime="08/26/2015 11:28:36" />
    <file relUrl="Payroll/ITaxEmployeeContribution.aspx" publishTime="08/26/2015 11:28:37" />
    <file relUrl="Common/StateMaster.aspx" publishTime="08/26/2015 11:28:32" />
    <file relUrl="Accounts/BankReconsiliation.aspx" publishTime="08/26/2015 11:28:29" />
    <file relUrl="Accounts/CreatefinYr.aspx" publishTime="08/26/2015 11:28:30" />
    <file relUrl="Logout.aspx" publishTime="08/26/2015 11:31:20" />
    <file relUrl="Accounts/RPTContraVoucher.aspx" publishTime="08/26/2015 11:28:30" />
    <file relUrl="Admission/BTechRegistration.aspx" publishTime="08/26/2015 11:28:31" />
    <file relUrl="Student/StudentPhoto/9.jpg" publishTime="08/26/2015 11:28:46" />
    <file relUrl="Images/AccecptButton.JPG" publishTime="08/26/2015 11:28:35" />
    <file relUrl="Admission/Thanks.aspx" publishTime="08/26/2015 11:28:31" />
    <file relUrl="bin/BusinessLayer.pdb" publishTime="05/23/2017 15:01:27" />
    <file relUrl="Common/App_LocalResources/RoleAccessLevel.aspx.resx" publishTime="08/26/2015 11:28:31" />
    <file relUrl="Student/AllFees.aspx" publishTime="08/26/2015 11:28:44" />
    <file relUrl="Images/bing.JPG" publishTime="08/26/2015 11:28:35" />
    <file relUrl="Images/NO.JPG" publishTime="08/26/2015 11:28:36" />
    <file relUrl="Images/Signature.JPG" publishTime="08/26/2015 11:28:36" />
    <file relUrl="GoogleCrome.htm" publishTime="08/26/2015 11:31:19" />
    <file relUrl="Student/StudentPhoto/10.jpg" publishTime="08/26/2015 11:28:46" />
    <file relUrl="Images/print-icon.JPG" publishTime="08/26/2015 11:28:36" />
    <file relUrl="bin/Microsoft.Office.Interop.Excel.xml" publishTime="01/18/2011 21:08:54" />
    <file relUrl="Images/RejectButton.JPG" publishTime="08/26/2015 11:28:36" />
    <file relUrl="Student/Fees.aspx" publishTime="08/26/2015 11:28:45" />
    <file relUrl="Scripts/ga.js" publishTime="08/26/2015 11:28:44" />
    <file relUrl="Accounts/RPTProfitLoss.aspx" publishTime="08/26/2015 11:28:30" />
    <file relUrl="Common/EmployeePhoto/1.jpg" publishTime="08/26/2015 11:28:31" />
    <file relUrl="Student/StudentPhoto/Male.JPG" publishTime="08/26/2015 11:28:46" />
    <file relUrl="Images/button_highlight.png" publishTime="08/26/2015 11:28:35" />
    <file relUrl="Student/ApproveStudent.aspx" publishTime="08/26/2015 11:28:44" />
    <file relUrl="Common/PopupPTaxDetails.aspx" publishTime="08/26/2015 11:28:32" />
    <file relUrl="Accounts/ContraVoucher.aspx" publishTime="08/26/2015 11:28:30" />
    <file relUrl="Images/button_home.png" publishTime="08/26/2015 11:28:35" />
    <file relUrl="Common/DbBackupRestore.aspx" publishTime="08/26/2015 11:28:31" />
    <file relUrl="Accounts/RPTTrailBalance.aspx" publishTime="08/26/2015 11:28:30" />
    <file relUrl="Student/StudentPhoto/14.jpg" publishTime="08/26/2015 11:28:46" />
    <file relUrl="Images/header_inner_corners.png" publishTime="08/26/2015 11:28:35" />
    <file relUrl="Images/close_pop.png" publishTime="08/26/2015 11:28:35" />
    <file relUrl="Student/StudentPhoto/15.jpg" publishTime="08/26/2015 11:28:46" />
    <file relUrl="Scripts/jquery-1.10.2.min.js" publishTime="08/26/2015 11:28:44" />
    <file relUrl="Payroll/PaySlip.aspx" publishTime="08/26/2015 11:28:38" />
    <file relUrl="Images/background.png" publishTime="08/26/2015 11:28:35" />
    <file relUrl="Images/button_highlight_selected.png" publishTime="08/26/2015 11:28:35" />
    <file relUrl="Common/GradeMaster.aspx" publishTime="08/26/2015 11:28:32" />
    <file relUrl="HR/LeaveStockUpdate.aspx" publishTime="08/26/2015 11:28:35" />
    <file relUrl="Images/application_double.png" publishTime="08/26/2015 11:28:35" />
    <file relUrl="Payroll/LoanEntryDetails.aspx" publishTime="08/26/2015 11:28:38" />
    <file relUrl="Accounts/PrintContraVoucher.aspx" publishTime="08/26/2015 11:28:30" />
    <file relUrl="Payroll/PtaxChallan.aspx" publishTime="08/26/2015 11:28:38" />
    <file relUrl="Scripts/jquery.ui.selectmenu.js" publishTime="08/26/2015 11:28:44" />
    <file relUrl="Images/button.JPG" publishTime="08/26/2015 11:28:35" />
    <file relUrl="Accounts/RPTLedger.aspx" publishTime="08/26/2015 11:28:30" />
    <file relUrl="Accounts/FundTransfer.aspx" publishTime="08/26/2015 11:28:30" />
    <file relUrl="Styles/login-box.css" publishTime="08/26/2015 11:28:46" />
    <file relUrl="Common/EmployeeAttendanceNew.aspx" publishTime="08/26/2015 11:28:31" />
    <file relUrl="Payroll/ITaxSectionMaster.aspx" publishTime="08/26/2015 11:28:38" />
    <file relUrl="Accounts/StudentJournalTran.aspx" publishTime="08/26/2015 11:28:31" />
    <file relUrl="Common/EmployeeTermsAndCondition.aspx" publishTime="08/26/2015 11:28:32" />
    <file relUrl="Scripts/webtrends.js" publishTime="08/26/2015 11:28:44" />
    <file relUrl="Images/header_background.png" publishTime="08/26/2015 11:28:35" />
    <file relUrl="Images/Content.JPG" publishTime="08/26/2015 11:28:35" />
    <file relUrl="Accounts/RPTShowGrid.aspx" publishTime="08/26/2015 11:28:30" />
    <file relUrl="HR/DirectorLeaveApproval.aspx" publishTime="08/26/2015 11:28:33" />
    <file relUrl="bin/BusinessLayer.dll" publishTime="05/23/2017 15:01:28" />
    <file relUrl="HR/LeaveReportBalance.aspx" publishTime="08/26/2015 11:28:35" />
    <file relUrl="Accounts/AccountsGroup.aspx" publishTime="08/26/2015 11:28:29" />
    <file relUrl="Student/UserBaseApprovedStudentList.aspx" publishTime="08/26/2015 11:28:46" />
    <file relUrl="Scripts/smooth.menu.js" publishTime="08/26/2015 11:28:44" />
    <file relUrl="Images/ginger.jpg" publishTime="08/26/2015 11:28:35" />
    <file relUrl="HR/LeaveManagerChange.aspx" publishTime="08/26/2015 11:28:34" />
    <file relUrl="Admission/MTechRegistration.aspx" publishTime="08/26/2015 11:28:31" />
    <file relUrl="Scripts/webtrends.hm.js" publishTime="08/26/2015 11:28:44" />
    <file relUrl="HR/EmployeeIndividualReport.aspx" publishTime="08/26/2015 11:28:34" />
    <file relUrl="bin/DataAccess.dll" publishTime="05/23/2017 15:01:26" />
    <file relUrl="HR/EmpIndividualPrint.aspx" publishTime="08/26/2015 11:28:33" />
    <file relUrl="Student/StudentDropout.aspx" publishTime="08/26/2015 11:28:45" />
    <file relUrl="Accounts/PrintJournalVoucher.aspx" publishTime="08/26/2015 11:28:30" />
    <file relUrl="Accounts/RPTGridViewMgmnt.aspx" publishTime="08/26/2015 11:28:30" />
    <file relUrl="Common/SchoolMaster.aspx" publishTime="08/26/2015 11:28:32" />
    <file relUrl="Accounts/StudentOpeningBalance.aspx" publishTime="08/26/2015 11:28:31" />
    <file relUrl="Styles/reset.css" publishTime="08/26/2015 11:28:47" />
    <file relUrl="Student/StudentCreditBillEntry.aspx" publishTime="08/26/2015 11:28:45" />
    <file relUrl="Common/DesignationMaster.aspx" publishTime="08/26/2015 11:28:31" />
    <file relUrl="Images/delete_icon.gif" publishTime="08/26/2015 11:28:35" />
    <file relUrl="Payroll/EmployeeAdditionalHeadSetting.aspx" publishTime="08/26/2015 11:28:37" />
    <file relUrl="Student/StudentPhoto/13.jpg" publishTime="08/26/2015 11:28:46" />
    <file relUrl="Common/PaybandMaster.aspx" publishTime="08/26/2015 11:28:32" />
    <file relUrl="Common/EmployeePhoto/Female.JPG" publishTime="08/26/2015 11:28:32" />
    <file relUrl="Images/Unauthorized.jpg" publishTime="08/26/2015 11:28:37" />
    <file relUrl="Student/MTechRegistration.aspx" publishTime="08/02/2016 15:50:29" />
    <file relUrl="Payroll/EmployeeSalary.aspx" publishTime="07/16/2016 18:09:39" />
    <file relUrl="Scripts/smooth.js" publishTime="08/26/2015 11:28:44" />
    <file relUrl="Common/EmployeePhoto/Male.JPG" publishTime="08/26/2015 11:28:32" />
    <file relUrl="Images/logo-small.jpg" publishTime="08/26/2015 11:28:36" />
    <file relUrl="Images/menu_r_selected.png" publishTime="08/26/2015 11:28:36" />
    <file relUrl="Images/login_corners.png" publishTime="08/26/2015 11:28:35" />
    <file relUrl="Styles/Control.css" publishTime="07/18/2016 15:14:23" />
    <file relUrl="Images/page_white_copy.png" publishTime="08/26/2015 11:28:36" />
    <file relUrl="Payroll/EmployeeIncrementReport.aspx" publishTime="08/17/2016 13:58:29" />
    <file relUrl="Images/login-btn.png" publishTime="08/26/2015 11:28:35" />
    <file relUrl="Student/StudentPhoto/Female.JPG" publishTime="08/26/2015 11:28:46" />
    <file relUrl="Images/Student.jpg" publishTime="08/26/2015 11:28:36" />
    <file relUrl="Payroll/MonthlyPFRegister.aspx" publishTime="01/13/2017 13:17:25" />
    <file relUrl="Common/CollegeMaster.aspx" publishTime="08/26/2015 11:28:31" />
    <file relUrl="Images/plus.png" publishTime="08/26/2015 11:28:36" />
    <file relUrl="Scripts/rum.js" publishTime="08/26/2015 11:28:44" />
    <file relUrl="Scripts/jquery-1.6.4.min.js" publishTime="08/26/2015 11:28:44" />
    <file relUrl="SuperAdmin.Master" publishTime="08/26/2015 11:31:20" />
    <file relUrl="Images/warning.png" publishTime="08/26/2015 11:28:37" />
    <file relUrl="Admission/MBARegistration.aspx" publishTime="08/26/2015 11:28:31" />
    <file relUrl="Student/Attendance.aspx" publishTime="08/26/2015 11:28:44" />
    <file relUrl="Accounts/CostCentre.aspx" publishTime="08/26/2015 11:28:30" />
    <file relUrl="Accounts/MoneyReceiptMgmnt.aspx" publishTime="08/26/2015 11:28:30" />
    <file relUrl="Images/minus.JPG" publishTime="08/26/2015 11:28:36" />
    <file relUrl="Images/HR.jpg" publishTime="08/26/2015 11:28:35" />
    <file relUrl="Images/remove.gif" publishTime="08/26/2015 11:28:36" />
    <file relUrl="HR/LeaveList.aspx" publishTime="08/26/2015 11:28:34" />
    <file relUrl="Images/logoBTech.JPG" publishTime="08/26/2015 11:28:36" />
    <file relUrl="Payroll/TdsChallan.aspx" publishTime="08/26/2015 11:28:38" />
    <file relUrl="Payroll/Form16.aspx" publishTime="08/26/2015 11:28:37" />
    <file relUrl="Images/print.gif" publishTime="08/26/2015 11:28:36" />
    <file relUrl="Scripts/jquery.flot.min.js" publishTime="08/26/2015 11:28:44" />
    <file relUrl="Accounts/StudentCautionMoneySummaryReport.aspx" publishTime="08/26/2015 11:28:31" />
    <file relUrl="Accounts/MoneyReceipt.aspx" publishTime="08/26/2015 11:28:30" />
    <file relUrl="Common/PTax.aspx" publishTime="08/26/2015 11:28:32" />
    <file relUrl="Images/cog.png" publishTime="08/26/2015 11:28:35" />
    <file relUrl="Images/StudentCampusDirector.JPG" publishTime="08/26/2015 11:28:36" />
    <file relUrl="Scripts/smooth.form.js" publishTime="08/26/2015 11:28:44" />
    <file relUrl="Student/SubjectMaster.aspx" publishTime="08/26/2015 14:39:55" />
    <file relUrl="bin/Microsoft.Vbe.Interop.dll" publishTime="01/18/2011 18:27:04" />
    <file relUrl="Student/BTechRegistrationPrint.aspx" publishTime="07/18/2016 15:52:49" />
    <file relUrl="Payroll/HTMLPage1.htm" publishTime="08/26/2015 11:28:37" />
    <file relUrl="Scripts/smooth.chart.js" publishTime="08/26/2015 11:28:44" />
    <file relUrl="Payroll/SalaryHeadUpdation.aspx" publishTime="08/26/2015 11:28:38" />
    <file relUrl="Common/PopupOfficialDetails.aspx" publishTime="01/13/2017 13:15:50" />
    <file relUrl="Payroll/ITaxEmployeePrevEmplDetails.aspx" publishTime="08/26/2015 11:28:37" />
    <file relUrl="Accounts/StudentOutstandingReport.aspx" publishTime="08/26/2015 11:28:31" />
    <file relUrl="HR/DirectorClaimApproval.aspx" publishTime="08/26/2015 11:28:33" />
    <file relUrl="HR/ExpenseType.aspx" publishTime="08/26/2015 11:28:34" />
    <file relUrl="Student/PopUpChangeStudentDetail.aspx" publishTime="08/26/2015 11:28:45" />
    <file relUrl="Student/MBARegistration.aspx" publishTime="07/18/2016 16:19:16" />
    <file relUrl="Common/PopupQualification.aspx" publishTime="08/26/2015 11:28:32" />
    <file relUrl="Accounts/StudentBillDetails.aspx" publishTime="05/23/2017 15:45:38" />
    <file relUrl="Scripts/jquery-ui-1.8.16.custom.min.js" publishTime="08/26/2015 11:28:44" />
    <file relUrl="Accounts/StudentAdvanceRefund.aspx" publishTime="08/26/2015 11:28:31" />
    <file relUrl="HR/DirectLeaveEntry.aspx" publishTime="08/26/2015 11:28:33" />
    <file relUrl="Student/StudentPhoto/6514.jpg" publishTime="08/26/2015 11:28:46" />
    <file relUrl="Images/calendar(1).png" publishTime="08/26/2015 11:28:35" />
    <file relUrl="MasterAdmin.Master" publishTime="01/13/2017 12:37:57" />
    <file relUrl="DBQuery.aspx" publishTime="08/26/2015 11:31:19" />
    <file relUrl="Accounts/RPTGeneralLedger.aspx" publishTime="08/26/2015 11:28:30" />
    <file relUrl="HR/LeaveSetting.aspx" publishTime="08/26/2015 11:28:35" />
    <file relUrl="Student/DiplomaRegistrationPrint.aspx" publishTime="07/18/2016 15:07:08" />
    <file relUrl="Common/DistrictMaster.aspx" publishTime="08/26/2015 11:28:31" />
    <file relUrl="Student/StudentPhoto/6491.jpg" publishTime="08/26/2015 11:28:46" />
    <file relUrl="Images/title_link.png" publishTime="08/26/2015 11:28:37" />
    <file relUrl="Images/error.png" publishTime="08/26/2015 11:28:35" />
    <file relUrl="Payroll/PTaxDetailsReport.aspx" publishTime="04/13/2017 16:17:07" />
    <file relUrl="Common/RoleAccessLevel.aspx" publishTime="05/22/2017 17:25:36" />
    <file relUrl="Common/EmployeeIDCard.aspx" publishTime="08/26/2015 11:28:31" />
    <file relUrl="Student/HostelFees.aspx" publishTime="08/26/2015 11:28:45" />
    <file relUrl="Default.aspx" publishTime="08/26/2015 11:31:19" />
    <file relUrl="Student/StudentSubjectMapping.aspx" publishTime="08/26/2015 11:28:46" />
    <file relUrl="Scripts/jquery-1.4.1.js" publishTime="08/26/2015 11:24:15" />
    <file relUrl="Images/title.png" publishTime="08/26/2015 11:28:37" />
    <file relUrl="Accounts/AccountGroupType.aspx" publishTime="08/26/2015 11:28:29" />
    <file relUrl="Scripts/smooth.dialog.js" publishTime="08/26/2015 11:28:44" />
    <file relUrl="Images/Payroll.jpg" publishTime="08/26/2015 11:28:36" />
    <file relUrl="Images/title_tab_selected.png" publishTime="08/26/2015 11:28:37" />
    <file relUrl="Payroll/Form16Print.aspx" publishTime="08/26/2015 11:28:37" />
    <file relUrl="Scripts/smooth.autocomplete.js" publishTime="08/26/2015 11:28:44" />
    <file relUrl="Images/PO.jpg" publishTime="08/26/2015 11:28:36" />
    <file relUrl="Payroll/EmployeeDeductionSetting.aspx" publishTime="08/26/2015 11:28:37" />
    <file relUrl="Images/menu_l_selected.png" publishTime="08/26/2015 11:28:36" />
    <file relUrl="Common/StatutorySalaryConfig.aspx" publishTime="08/26/2015 11:28:32" />
    <file relUrl="Images/college.PNG" publishTime="08/26/2015 11:28:35" />
    <file relUrl="Student/TeacherSubjectMapping.aspx" publishTime="08/26/2015 14:03:35" />
    <file relUrl="Payroll/MonthlySalaryGeneration.aspx" publishTime="08/26/2015 11:28:38" />
    <file relUrl="Images/Ruppees.jpg" publishTime="08/26/2015 11:28:36" />
    <file relUrl="Accounts/StudentConsolidatedOutstandingReport.aspx" publishTime="08/26/2015 11:28:31" />
    <file relUrl="Common/DepartmentMaster.aspx" publishTime="08/26/2015 11:28:31" />
    <file relUrl="Accounts/PurchaseBillPayment.aspx" publishTime="08/26/2015 11:28:30" />
    <file relUrl="Accounts/RPTGridViewDiploma.aspx" publishTime="08/26/2015 11:28:30" />
    <file relUrl="Web.config" publishTime="07/18/2016 16:32:28" />
    <file relUrl="Student/allStudent.aspx" publishTime="07/18/2016 15:16:04" />
    <file relUrl="HR/LeaveApplicationConfig.aspx" publishTime="08/26/2015 11:28:34" />
    <file relUrl="bin/SKFGI.pdb" publishTime="05/23/2017 16:37:37" />
    <file relUrl="Student/BulkSubjectAttendance.aspx" publishTime="08/26/2015 14:04:38" />
    <file relUrl="Images/TermsAndCondition.JPG" publishTime="08/26/2015 11:28:36" />
    <file relUrl="Student/BTechRegistration.aspx" publishTime="08/02/2016 15:42:50" />
    <file relUrl="Scripts/jquery-1.4.1.min.js" publishTime="08/26/2015 11:24:15" />
    <file relUrl="Images/edit_icon.gif" publishTime="08/26/2015 11:28:35" />
    <file relUrl="Images/notice.png" publishTime="08/26/2015 11:28:36" />
    <file relUrl="PurchaseOrder/PurchaseOrderEntry.aspx" publishTime="12/11/2015 15:43:14" />
    <file relUrl="Payroll/AllEmployeesPaySlip.aspx" publishTime="08/26/2015 11:28:37" />
    <file relUrl="Images/Module.JPG" publishTime="08/26/2015 11:28:36" />
    <file relUrl="bin/Microsoft.Office.Interop.Excel.dll" publishTime="01/18/2011 18:27:04" />
    <file relUrl="HR/PopUpLeave.aspx" publishTime="08/26/2015 11:28:35" />
    <file relUrl="Images/cross.png" publishTime="08/26/2015 11:28:35" />
    <file relUrl="Images/minus.png" publishTime="08/26/2015 11:28:36" />
    <file relUrl="Images/ajax-loader.gif" publishTime="08/26/2015 11:28:35" />
    <file relUrl="Images/close.gif" publishTime="08/26/2015 11:28:35" />
    <file relUrl="StudentMaster.Master" publishTime="08/26/2015 11:31:20" />
    <file relUrl="Scripts/jquery-1.4.1-vsdoc.js" publishTime="08/26/2015 11:24:15" />
    <file relUrl="bin/DataAccess.pdb" publishTime="05/23/2017 15:01:26" />
    <file relUrl="Accounts/ChangeFinYr.aspx" publishTime="08/26/2015 11:28:29" />
    <file relUrl="Student/FeesHeadMaster.aspx" publishTime="08/26/2015 11:28:45" />
    <file relUrl="UserControl/Message.ascx" publishTime="08/26/2015 11:28:29" />
    <file relUrl="Styles/style.css" publishTime="08/26/2015 11:28:47" />
    <file relUrl="Accounts/StudentFeesCollection.aspx" publishTime="08/26/2015 11:28:31" />
    <file relUrl="Student/StudentBillEntry.aspx" publishTime="08/26/2015 11:28:45" />
    <file relUrl="Images/header_inner.png" publishTime="08/26/2015 11:28:35" />
    <file relUrl="Images/login-box-backg.png" publishTime="08/26/2015 11:28:35" />
    <file relUrl="Images/minus.gif" publishTime="08/26/2015 11:28:36" />
    <file relUrl="Images/calendar.png" publishTime="08/26/2015 11:28:35" />
  </publishProfile>
</publishData>